odoo/addons/test_ssi_custom_information_mixin/README.rst
odoo/addons/test_ssi_custom_information_mixin/__init__.py
odoo/addons/test_ssi_custom_information_mixin/__manifest__.py
odoo/addons/test_ssi_custom_information_mixin/models/__init__.py
odoo/addons/test_ssi_custom_information_mixin/models/test_custom_information.py
odoo/addons/test_ssi_custom_information_mixin/security/ir.model.access.csv
odoo/addons/test_ssi_custom_information_mixin/static/description/icon.png
odoo/addons/test_ssi_custom_information_mixin/views/test_custom_information_views.xml
odoo14_addon_test_ssi_custom_information_mixin-14.0.2.1.0.dist-info/METADATA
odoo14_addon_test_ssi_custom_information_mixin-14.0.2.1.0.dist-info/WHEEL
odoo14_addon_test_ssi_custom_information_mixin-14.0.2.1.0.dist-info/top_level.txt
odoo14_addon_test_ssi_custom_information_mixin-14.0.2.1.0.dist-info/RECORD
